colorforms/__init__.py
colorforms/__main__.py
colorforms-1.0.1.dist-info/entry_points.txt
colorforms-1.0.1.dist-info/LICENSE
colorforms-1.0.1.dist-info/WHEEL
colorforms-1.0.1.dist-info/METADATA
colorforms-1.0.1.dist-info/RECORD
