Metadata-Version: 2.1
Name: colorforms
Version: 1.0.1
Summary: Convert colors from one format to another.
Author-email: Leon Dionne <ldionne@dridesign.sh.cn>
Classifier: License :: OSI Approved :: GNU General Public License v3 or later (GPLv3+)
Project-URL: Home, https://github.com/Zen-Master-SoSo/colorforms
